nhsuk_frontend_jinja/__init__.py
nhsuk_frontend_jinja/templates/nhsuk/components/action-link/macro.jinja
nhsuk_frontend_jinja/templates/nhsuk/components/action-link/template.jinja
nhsuk_frontend_jinja/templates/nhsuk/components/back-link/macro.jinja
nhsuk_frontend_jinja/templates/nhsuk/components/back-link/template.jinja
nhsuk_frontend_jinja/templates/nhsuk/components/breadcrumb/macro.jinja
nhsuk_frontend_jinja/templates/nhsuk/components/breadcrumb/template.jinja
nhsuk_frontend_jinja/templates/nhsuk/components/button/macro.jinja
nhsuk_frontend_jinja/templates/nhsuk/components/button/template.jinja
nhsuk_frontend_jinja/templates/nhsuk/components/card/macro.jinja
nhsuk_frontend_jinja/templates/nhsuk/components/card/template.jinja
nhsuk_frontend_jinja/templates/nhsuk/components/character-count/macro.jinja
nhsuk_frontend_jinja/templates/nhsuk/components/character-count/template.jinja
nhsuk_frontend_jinja/templates/nhsuk/components/checkboxes/macro.jinja
nhsuk_frontend_jinja/templates/nhsuk/components/checkboxes/template.jinja
nhsuk_frontend_jinja/templates/nhsuk/components/contents-list/macro.jinja
nhsuk_frontend_jinja/templates/nhsuk/components/contents-list/template.jinja
nhsuk_frontend_jinja/templates/nhsuk/components/date-input/macro.jinja
nhsuk_frontend_jinja/templates/nhsuk/components/date-input/template.jinja
nhsuk_frontend_jinja/templates/nhsuk/components/details/macro.jinja
nhsuk_frontend_jinja/templates/nhsuk/components/details/template.jinja
nhsuk_frontend_jinja/templates/nhsuk/components/do-dont-list/macro.jinja
nhsuk_frontend_jinja/templates/nhsuk/components/do-dont-list/template.jinja
nhsuk_frontend_jinja/templates/nhsuk/components/error-message/macro.jinja
nhsuk_frontend_jinja/templates/nhsuk/components/error-message/template.jinja
nhsuk_frontend_jinja/templates/nhsuk/components/error-summary/macro.jinja
nhsuk_frontend_jinja/templates/nhsuk/components/error-summary/template.jinja
nhsuk_frontend_jinja/templates/nhsuk/components/fieldset/macro.jinja
nhsuk_frontend_jinja-0.7.1.dist-info/METADATA
nhsuk_frontend_jinja-0.7.1.dist-info/WHEEL
nhsuk_frontend_jinja-0.7.1.dist-info/RECORD
