Metadata-Version: 2.4
Name: nhsuk-frontend-jinja
Version: 0.7.1
Summary: A port of NHS.UK frontend templates for the Jinja templating engine.
License: MIT
Author: Mat Moore
Author-email: MatMoore@users.noreply.github.com
Requires-Python: >=3.11
Classifier: License :: OSI Approved :: MIT License
Classifier: Programming Language :: Python :: 3
Classifier: Programming Language :: Python :: 3.11
Classifier: Programming Language :: Python :: 3.12
Classifier: Programming Language :: Python :: 3.13
Classifier: Programming Language :: Python :: 3.14
Requires-Dist: jinja2 (>=3.1.6,<4.0.0)
